serdespy/__init__.py
serdespy/chmodel.py
serdespy/eye_diagram.py
serdespy/four_port_to_diff.py
serdespy/prs.py
serdespy/receiver.py
serdespy/reedsolo.py
serdespy/rs_code.py
serdespy/signal.py
serdespy/transmitter.py
serdespy-1.0.dist-info/LICENSE
serdespy-1.0.dist-info/METADATA
serdespy-1.0.dist-info/WHEEL
serdespy-1.0.dist-info/top_level.txt
serdespy-1.0.dist-info/RECORD
