Metadata-Version: 2.1
Name: serdespy
Version: 1.0
Summary: Library for system-level SerDes modelling and Simulation
Author: Richard Barrie
Author-email: richard.barrie@mail.utoronto.ca
Classifier: Development Status :: 3 - Alpha
Classifier: License :: OSI Approved :: MIT License
Classifier: Programming Language :: Python :: 3.7
Classifier: Programming Language :: Python :: 3.8
Classifier: Programming Language :: Python :: 3.9
License-File: LICENSE
Requires-Dist: numpy
Requires-Dist: scipy
Requires-Dist: matplotlib
Requires-Dist: scikit-rf
Requires-Dist: samplerate
